sequenceDiagram.py
sequenceDiagram-0.0.3.dist-info/LICENSE
sequenceDiagram-0.0.3.dist-info/METADATA
sequenceDiagram-0.0.3.dist-info/WHEEL
sequenceDiagram-0.0.3.dist-info/top_level.txt
sequenceDiagram-0.0.3.dist-info/RECORD
