Metadata-Version: 2.1
Name: sequenceDiagram
Version: 0.0.3
Summary: library to generate seqeuence diagram for python code
Author-email: Brijesh Kulkarni <brijesh.kulkarni@gmail.com>
Project-URL: Homepage, https://github.com/brijeshkulkarni/sequenceDiagram
Project-URL: Issues, https://github.com/brijeshkulkarni/sequenceDiagram/issues
Classifier: Programming Language :: Python :: 3
Classifier: License :: OSI Approved :: MIT License
Classifier: Operating System :: OS Independent
Requires-Python: >=3
License-File: LICENSE
